{"GlobalPropertiesHash":"CmWTfiNO4K1kWlr3Qsz22ZPgGmGhepverNhsJO6Cew0=","FingerprintPatternsHash":"gq3WsqcKBUGTSNle7RKKyXRIwh7M8ccEqOqYvIzoM04=","PropertyOverridesHash":"8ZRc1sGeVrPBx4lD717BgRaQekyh78QKV9SKsdt638U=","InputHashes":["9J\u002BrH6C0jGznme3FUvqyqIW6H3lqAIycF3yxpsurGDU=","PECqm5POePPUFrbfr8zl9NEoxcBym6PxHm6Yde7ZtFE=","B5T/V2u72E3muhcSCZw07maxrvsWc0ovd8dUQ3eElL0=","QbEZFAu1gk052Klth5SKu4yht90tQxjXFKK0\u002BZZHImA=","SshUYdIiKI/DrDYcAsRnsJ2ykWeHFO6sBOsHZDdK71I="],"CachedAssets":{"B5T/V2u72E3muhcSCZw07maxrvsWc0ovd8dUQ3eElL0=":{"Identity":"C:\\Users\\avmapalad\\Desktop\\MyProjects\\RST\\wwwroot\\transactions.html","SourceId":"RelationshipVisualizer","SourceType":"Discovered","ContentRoot":"C:\\Users\\avmapalad\\Desktop\\MyProjects\\RST\\wwwroot\\","BasePath":"/","RelativePath":"transactions#[.{fingerprint}]?.html","AssetKind":"All","AssetMode":"All","AssetRole":"Primary","AssetMergeBehavior":null,"AssetMergeSource":"","RelatedAsset":null,"AssetTraitName":null,"AssetTraitValue":null,"Fingerprint":"14d459ff38","Integrity":"YbTt5ZJnEgAm7HTloKuSHFPbj/XrxtdeqClNw3\u002Bjf4Q=","CopyToOutputDirectory":"Never","CopyToPublishDirectory":"PreserveNewest","OriginalItemSpec":"wwwroot\\transactions.html","FileLength":50322,"LastWriteTime":"2026-07-08T00:54:58.5542757+00:00"},"PECqm5POePPUFrbfr8zl9NEoxcBym6PxHm6Yde7ZtFE=":{"Identity":"C:\\Users\\avmapalad\\Desktop\\MyProjects\\RST\\wwwroot\\index.html","SourceId":"RelationshipVisualizer","SourceType":"Discovered","ContentRoot":"C:\\Users\\avmapalad\\Desktop\\MyProjects\\RST\\wwwroot\\","BasePath":"/","RelativePath":"index#[.{fingerprint}]?.html","AssetKind":"All","AssetMode":"All","AssetRole":"Primary","AssetMergeBehavior":null,"AssetMergeSource":"","RelatedAsset":null,"AssetTraitName":null,"AssetTraitValue":null,"Fingerprint":"bwkrz0cmke","Integrity":"dRoR7gYErZDVkANRlEJ62bNlQ5/JExEmAy\u002BQgZtEUjQ=","CopyToOutputDirectory":"Never","CopyToPublishDirectory":"PreserveNewest","OriginalItemSpec":"wwwroot\\index.html","FileLength":20283,"LastWriteTime":"2026-07-02T05:12:02.3474416+00:00"},"9J\u002BrH6C0jGznme3FUvqyqIW6H3lqAIycF3yxpsurGDU=":{"Identity":"C:\\Users\\avmapalad\\Desktop\\MyProjects\\RST\\wwwroot\\css\\app.css","SourceId":"RelationshipVisualizer","SourceType":"Discovered","ContentRoot":"C:\\Users\\avmapalad\\Desktop\\MyProjects\\RST\\wwwroot\\","BasePath":"/","RelativePath":"css/app#[.{fingerprint}]?.css","AssetKind":"All","AssetMode":"All","AssetRole":"Primary","AssetMergeBehavior":null,"AssetMergeSource":"","RelatedAsset":null,"AssetTraitName":null,"AssetTraitValue":null,"Fingerprint":"10oh9k12cm","Integrity":"P2Poocg8sEDTySHZwdBMqgafzUG5q44FHPzC5sWKIs0=","CopyToOutputDirectory":"Never","CopyToPublishDirectory":"PreserveNewest","OriginalItemSpec":"wwwroot\\css\\app.css","FileLength":31068,"LastWriteTime":"2026-07-08T00:54:30.6663448+00:00"},"QbEZFAu1gk052Klth5SKu4yht90tQxjXFKK0\u002BZZHImA=":{"Identity":"C:\\Users\\avmapalad\\Desktop\\MyProjects\\RST\\wwwroot\\vis-network.min.js","SourceId":"RelationshipVisualizer","SourceType":"Discovered","ContentRoot":"C:\\Users\\avmapalad\\Desktop\\MyProjects\\RST\\wwwroot\\","BasePath":"/","RelativePath":"vis-network.min#[.{fingerprint}]?.js","AssetKind":"All","AssetMode":"All","AssetRole":"Primary","AssetMergeBehavior":null,"AssetMergeSource":"","RelatedAsset":null,"AssetTraitName":null,"AssetTraitValue":null,"Fingerprint":"vdx4awg90m","Integrity":"/XMOMEpbh3qTeolr6VNueXTcRz2KyH\u002BmZkS85Sy1\u002BOQ=","CopyToOutputDirectory":"Never","CopyToPublishDirectory":"PreserveNewest","OriginalItemSpec":"wwwroot\\vis-network.min.js","FileLength":643839,"LastWriteTime":"2026-06-23T06:33:51.4718292+00:00"}},"CachedCopyCandidates":{}}